mext/__init__.py
mext/mext.py
mext/mext_parser.py
mext/libs/config_loader.py
mext/libs/utils.py
mext/scripts/render_mext.py
mext_lang-0.1.1.dist-info/LICENSE
mext_lang-0.1.1.dist-info/METADATA
mext_lang-0.1.1.dist-info/WHEEL
mext_lang-0.1.1.dist-info/entry_points.txt
mext_lang-0.1.1.dist-info/top_level.txt
mext_lang-0.1.1.dist-info/RECORD
