Metadata-Version: 2.1
Name: mext-lang
Version: 0.1.1
Summary: Mext is a powerful text template language designed for crafting prompts for LLM models.
Author-email: Dongning Chen <donny.hikari@gmail.com>
License: GNU GENERAL PUBLIC LICENSE
Project-URL: Homepage, https://github.com/donny-hikari/mext
Project-URL: Repository, https://github.com/donny-hikari/mext
Classifier: Programming Language :: Python :: 3
Classifier: License :: OSI Approved :: GNU General Public License v3 (GPLv3)
Classifier: Operating System :: OS Independent
Requires-Python: >=3.8
License-File: LICENSE
Requires-Dist: pyyaml>=5.1
